anomaly_detection_toolkit/__init__.py
anomaly_detection_toolkit/autoencoders.py
anomaly_detection_toolkit/base.py
anomaly_detection_toolkit/ensemble.py
anomaly_detection_toolkit/ml_methods.py
anomaly_detection_toolkit/statistical.py
anomaly_detection_toolkit/wavelet.py
anomaly_detection_toolkit-0.1.1.dist-info/licenses/LICENSE
anomaly_detection_toolkit-0.1.1.dist-info/METADATA
anomaly_detection_toolkit-0.1.1.dist-info/WHEEL
anomaly_detection_toolkit-0.1.1.dist-info/top_level.txt
anomaly_detection_toolkit-0.1.1.dist-info/RECORD
