Metadata-Version: 2.4
Name: anomaly-detection-toolkit
Version: 0.1.1
Summary: A comprehensive Python library for detecting anomalies in time series and multivariate data
Home-page: https://github.com/kylejones200/anomaly-detection-toolkit
Author: Kyle Jones
Author-email: Kyle Jones <kyletjones@gmail.com>
License: MIT
Project-URL: Homepage, https://github.com/kylejones200/anomaly-detection-toolkit
Project-URL: Documentation, https://anomaly-detection-toolkit.readthedocs.io/
Project-URL: Repository, https://github.com/kylejones200/anomaly-detection-toolkit
Project-URL: Issues, https://github.com/kylejones200/anomaly-detection-toolkit/issues
Keywords: anomaly-detection,outlier-detection,time-series,machine-learning,data-science,isolation-forest,autoencoder,wavelet
Classifier: Development Status :: 3 - Alpha
Classifier: Intended Audience :: Developers
Classifier: Intended Audience :: Science/Research
Classifier: License :: OSI Approved :: MIT License
Classifier: Operating System :: OS Independent
Classifier: Programming Language :: Python :: 3
Classifier: Programming Language :: Python :: 3.12
Classifier: Topic :: Scientific/Engineering
Classifier: Topic :: Scientific/Engineering :: Artificial Intelligence
Classifier: Topic :: Software Development :: Libraries :: Python Modules
Requires-Python: >=3.12
License-File: LICENSE
Requires-Dist: numpy>=1.20.0
Requires-Dist: pandas>=1.3.0
Requires-Dist: scikit-learn>=1.0.0
Requires-Dist: PyWavelets>=1.3.0
Provides-Extra: deep
Requires-Dist: torch>=1.9.0; extra == "deep"
Requires-Dist: tensorflow>=2.6.0; extra == "deep"
Provides-Extra: docs
Requires-Dist: sphinx>=7.0.0; extra == "docs"
Requires-Dist: sphinx-rtd-theme>=2.0.0; extra == "docs"
Requires-Dist: sphinx-autodoc-typehints>=1.24.0; extra == "docs"
Requires-Dist: myst-parser>=2.0.0; extra == "docs"
Provides-Extra: all
Requires-Dist: anomaly-detection-toolkit[deep,docs]; extra == "all"
Dynamic: author
Dynamic: home-page
Dynamic: license-file
Dynamic: requires-python
